MANIFEST.in
README.rst
base.cfg
bootstrap.py
buildout-plone3-multi-db.cfg
buildout-plone3-single-db.cfg
multidb-base.cfg
multidb-test-4.0.x.cfg
multidb-test-4.1.x.cfg
multidb-test-4.2.x.cfg
multidb-test-4.3.x.cfg
multidb.cfg
setup.py
singledb-base.cfg
singledb-test-4.0.x.cfg
singledb-test-4.1.x.cfg
singledb-test-4.2.x.cfg
singledb-test-4.3.x.cfg
singledb.cfg
docs/HISTORY.txt
docs/LICENSE.GPL
docs/LICENSE.txt
src/plone/__init__.py
src/plone.app.async.egg-info/PKG-INFO
src/plone.app.async.egg-info/SOURCES.txt
src/plone.app.async.egg-info/dependency_links.txt
src/plone.app.async.egg-info/entry_points.txt
src/plone.app.async.egg-info/namespace_packages.txt
src/plone.app.async.egg-info/not-zip-safe
src/plone.app.async.egg-info/requires.txt
src/plone.app.async.egg-info/top_level.txt
src/plone/app/__init__.py
src/plone/app/async/README.rst
src/plone/app/async/__init__.py
src/plone/app/async/config.py
src/plone/app/async/configure.zcml
src/plone/app/async/interfaces.py
src/plone/app/async/job.py
src/plone/app/async/multi_db_instance.zcml
src/plone/app/async/multi_db_worker.zcml
src/plone/app/async/retry.py
src/plone/app/async/service.py
src/plone/app/async/single_db_instance.zcml
src/plone/app/async/single_db_worker.zcml
src/plone/app/async/subscribers.py
src/plone/app/async/testing.py
src/plone/app/async/utils.py
src/plone/app/async/browser/__init__.py
src/plone/app/async/browser/configure.zcml
src/plone/app/async/browser/queue.pt
src/plone/app/async/browser/queue.py
src/plone/app/async/tests/__init__.py
src/plone/app/async/tests/base.py
src/plone/app/async/tests/funcs.py
src/plone/app/async/tests/test_callbacks.py
src/plone/app/async/tests/test_doctests.py
src/plone/app/async/tests/test_functional.py
src/plone/app/async/tests/test_job.py
src/plone/app/async/tests/test_resulthandler.py
src/plone/app/async/tests/test_setup.py
src/plone/app/async/tests/test_simplejob.py
src/plone/app/async/tests/test_timing.py
src/plone/app/async/tests/view.zcml