Metadata-Version: 1.1
Name: plone.app.async
Version: 1.7.0
Summary: Integration package for zc.async allowing asynchronous operations in Plone
Home-page: http://plone.org/products/plone.app.async
Author: Plone Foundation
Author-email: plone-developers@lists.sourceforge.net
License: GPL version 2
Download-URL: http://pypi.python.org/pypi/plone.app.async
Keywords: plone async asynchronous
Platform: Any
Classifier: Environment :: Web Environment
Classifier: Framework :: Plone
Classifier: Intended Audience :: Developers
Classifier: License :: OSI Approved :: GNU General Public License (GPL)
Classifier: Operating System :: OS Independent
Classifier: Programming Language :: Python
Classifier: Topic :: Software Development :: Libraries :: Python Modules
